MANIFEST.in
README.txt
setup.py
src/mredoc/__init__.py
src/mredoc/constants.py
src/mredoc/errors.py
src/mredoc/objects.py
src/mredoc.egg-info/PKG-INFO
src/mredoc.egg-info/SOURCES.txt
src/mredoc.egg-info/dependency_links.txt
src/mredoc.egg-info/requires.txt
src/mredoc.egg-info/top_level.txt
src/mredoc/resources/defaultstyle.css
src/mredoc/resources/style1.scss
src/mredoc/testing/Makefile
src/mredoc/testing/TrigonometryTriangle.svg
src/mredoc/testing/example1.py
src/mredoc/testing/example1.py~
src/mredoc/testing/example2.py
src/mredoc/testing/example2.py~
src/mredoc/testing/example3.py
src/mredoc/testing/example4.py
src/mredoc/testing/example_minimal1.py
src/mredoc/testing/example_minimal1.py~
src/mredoc/util/__init__.py
src/mredoc/util/misc.py
src/mredoc/util/removeemptysections.py
src/mredoc/util/toolchecker.py
src/mredoc/visitors/__init__.py
src/mredoc/visitors/base_actioner.py
src/mredoc/visitors/base_visitor.py
src/mredoc/visitors/block_numbering.py
src/mredoc/visitors/reference_resolver.py
src/mredoc/writers/__init__.py
src/mredoc/writers/html/__init__.py
src/mredoc/writers/html/xmlwitch.py
src/mredoc/writers/latex/__init__.py