Metadata-Version: 1.1
Name: mredoc
Version: 0.1
Summary: Tools for generation hierachical documents in HTML and PDF, primarily designed for building reports of computational models.
Home-page: https://github.com/mikehulluk/mredoc
Author: Mike Hull
Author-email: mikehulluk@gmail.com
License: BSD
Platform: UNKNOWN
Classifier: Development Status :: 3 - Alpha
Classifier: Topic :: Utilities
Classifier: License :: OSI Approved :: BSD License
